{
  "db_name": "PostgreSQL",
  "query": "\n        INSERT INTO\n            community_tier_list_entries(character, eidolon, average, variance, votes, total_votes)\n        VALUES\n            ($1, $2, $3, $4, $5, $6)\n        ON CONFLICT\n            (character, eidolon)\n        DO UPDATE SET\n            average = EXCLUDED.average,\n            variance = EXCLUDED.variance,\n            votes = EXCLUDED.votes,\n            total_votes = EXCLUDED.total_votes\n        ",
  "describe": {
    "columns": [],
    "parameters": {
      "Left": [
        "Int4",
        "Int4",
        "Float8",
        "Float8",
        "Int4",
        "Int4"
      ]
    },
    "nullable": []
  },
  "hash": "13b0125c6a2234f2f31a829590e230c7880102eb99c8099b5d3996ad5c88f3ae"
}
