{
  "db_name": "PostgreSQL",
  "query": "\n        INSERT INTO\n            warp_lc_light_cones(id, uid, light_cone, timestamp)\n        VALUES\n            ($1, $2, $3, $4)\n        ON CONFLICT\n            (id, uid)\n        DO UPDATE SET\n            light_cone = EXCLUDED.light_cone,\n            timestamp = EXCLUDED.timestamp\n        ",
  "describe": {
    "columns": [],
    "parameters": {
      "Left": [
        "Int8",
        "Int8",
        "Int4",
        "Timestamp"
      ]
    },
    "nullable": []
  },
  "hash": "c6b359088f23140b6b552a970e6d2eebeabb05e95738610de1afa6fd9a419ee3"
}
